[
  {
    "name": "cdk",
    "imageUri": "499333472133.dkr.ecr.us-east-1.amazonaws.com/wiremock-cloud-cdk:add-mock-host-otel",
    "metadata": {
      "sourceAction": "set manually",
      "sourceCommit": "set manually"
    }
  },
  {
    "name": "ui",
    "imageUri": "499333472133.dkr.ecr.us-east-1.amazonaws.com/wiremock-cloud-ui:chore_remove-switching-between-api-token-and-bearer",
    "metadata": {
      "sourceAction": "set manually",
      "sourceCommit": "set manually"
    }
  },
  {
    "name": "mothership",
    "imageUri": "499333472133.dkr.ecr.us-east-1.amazonaws.com/wiremock-cloud-mothership:1.1485.0",
    "metadata": {
      "sourceAction": "https://github.com/wiremock-inc/mothership/actions/runs/11935749934",
      "sourceCommit": "https://github.com/wiremock-inc/mothership/tree/26f95a684ffd13c5fdb91d1b41d04716201d1cb0"
    }
  },
  {
    "name": "mock-host",
    "imageUri": "499333472133.dkr.ecr.us-east-1.amazonaws.com/wiremock-cloud-mock-host:add-otel",
    "metadata": {
      "sourceAction": "set manually",
      "sourceCommit": "set manually"
    }
  },
  {
    "name": "admin",
    "imageUri": "499333472133.dkr.ecr.us-east-1.amazonaws.com/wiremock-cloud-admin:1.153.0",
    "metadata": {
      "sourceAction": "https://github.com/wiremock-inc/admin/actions/runs/11836083162",
      "sourceCommit": "https://github.com/wiremock-inc/admin/tree/0aed42a3579bfbba011e6a0a9556dbb1e8385928"
    }
  }
]
