[
  {
    "name": "cdk",
    "imageUri": "499333472133.dkr.ecr.us-east-1.amazonaws.com/wiremock-cloud-cdk:upgrade-superset",
    "metadata": {
      "sourceAction": "set manually",
      "sourceCommit": "set manually"
    }
  },
  {
    "name": "ui",
    "imageUri": "499333472133.dkr.ecr.us-east-1.amazonaws.com/wiremock-cloud-ui:0.442.0",
    "metadata": {
      "sourceAction": "set manually",
      "sourceCommit": "set manually"
    }
  },
  {
    "name": "mothership",
    "imageUri": "499333472133.dkr.ecr.us-east-1.amazonaws.com/wiremock-cloud-mothership:1.1107.0",
    "metadata": {
      "sourceAction": "https://github.com/wiremock-inc/mothership/actions/runs/8647120493",
      "sourceCommit": "https://github.com/wiremock-inc/mothership/tree/c9af8b7352c17414381eccd68c81752334b26e55"
    }
  },
  {
    "name": "mock-host",
    "imageUri": "499333472133.dkr.ecr.us-east-1.amazonaws.com/wiremock-cloud-mock-host:1.562.0",
    "metadata": {
      "sourceAction": "https://github.com/wiremock-inc/mock-host/actions/runs/8648269407",
      "sourceCommit": "https://github.com/wiremock-inc/mock-host/tree/6bb37365dd92f781ca9b7881948ffdab161a5ca1"
    }
  },
  {
    "name": "admin",
    "imageUri": "499333472133.dkr.ecr.us-east-1.amazonaws.com/wiremock-cloud-admin:1.111.0",
    "metadata": {
      "sourceAction": "https://github.com/wiremock-inc/admin/actions/runs/8528410053",
      "sourceCommit": "https://github.com/wiremock-inc/admin/tree/34c883ec36a29b85246e5746b17409d5447df895"
    }
  }
]
